mock_event_generator/__init__.py
mock_event_generator/alert_conditions.py
mock_event_generator/analize_utils.py
mock_event_generator/cache.py
mock_event_generator/cli.py
mock_event_generator/creators.py
mock_event_generator/exceptions.py
mock_event_generator/fetchers.py
mock_event_generator/gracedbs.py
mock_event_generator/models.py
mock_event_generator/replay.py
mock_event_generator/utils.py
mock_event_generator/validators.py
mock_event_generator-1.4.17.dist-info/METADATA
mock_event_generator-1.4.17.dist-info/WHEEL
mock_event_generator-1.4.17.dist-info/entry_points.txt
mock_event_generator-1.4.17.dist-info/top_level.txt
mock_event_generator-1.4.17.dist-info/RECORD
