Metadata-Version: 2.4
Name: mock_event_generator
Version: 1.4.17
Summary: Re-create gravitational wave pipeline events by time-shifting existing ones.
Author-email: Roberto De Pietri <roberto.depietri@unipr.it>, Pierre Chanial <pierre.chanial@apc.in2p3.fr>
Maintainer-email: Roberto De Pietri <roberto.depietri@unipr.it>, Pierre Chanial <pierre.chanial@apc.in2p3.fr>
Keywords: scientific computing
Classifier: Development Status :: 5 - Production/Stable
Classifier: Intended Audience :: Science/Research
Classifier: Topic :: Scientific/Engineering
Classifier: Topic :: Scientific/Engineering :: Astronomy
Classifier: Topic :: Scientific/Engineering :: Physics
Classifier: Operating System :: OS Independent
Classifier: Programming Language :: Python
Requires-Python: >=3.11
Requires-Dist: apischema
Requires-Dist: click<8.2.0
Requires-Dist: numpy
Requires-Dist: matplotlib
Requires-Dist: astropy
Requires-Dist: mocpy
Requires-Dist: certifi
Requires-Dist: cryptography
Requires-Dist: lalsuite
Requires-Dist: ligo-gracedb
Requires-Dist: ligo-skymap
Requires-Dist: lxml
Requires-Dist: data-science-types
Requires-Dist: igwn-ligolw
Requires-Dist: requests
Requires-Dist: trio
Requires-Dist: typer[all]
Provides-Extra: tests
Requires-Dist: lalsuite; extra == "tests"
Requires-Dist: pytest; extra == "tests"
Requires-Dist: pytest-cov; extra == "tests"
Requires-Dist: pytest-gracedb>=0.7.2; extra == "tests"
Requires-Dist: pytest-mock; extra == "tests"
Requires-Dist: pytest-socket; extra == "tests"
Requires-Dist: pytest-trio; extra == "tests"
Requires-Dist: pytest-freezegun; extra == "tests"
Requires-Dist: responses; extra == "tests"
Requires-Dist: setuptools_scm[toml]; extra == "tests"
